{
  "id": "reinhard-gehlen-conclusion",
  "title": "Reinhard Gehlen – Conclusion",
  "status": "published",
  "authors": [
    "admin"
  ],
  "excerpt": "I have finally finished up my paper on Reinhard Gehlen. The final version was due today and it is a great relief to have it finished. I wrote up a brief summary of how the Gehlen Organization came to be on my German blog, but I will write a rough translation of it here. Gehlen &#8230; more &#x2192;\n",
  "categories": [
    "20th-century-german-history",
    "german-history"
  ],
  "tags": [
    "Reinhard Gehlen"
  ],
  "publishedDate": "2009-05-05T17:11:41",
  "updatedAt": "2012-01-06T22:51:15",
  "wordpressId": 608
}