{
  "id": "wyoming-territorial-prison-museum-website",
  "title": "Wyoming Territorial Prison Museum Website",
  "status": "published",
  "authors": [
    "admin"
  ],
  "excerpt": "For the past couple of weeks in between final projects for the university, I&#8217;ve been working on the website for the Wyoming Territorial Prison Museum. Originally I was going to do an internship there, but because that fell through due to timing issues, I was just commissioned instead to do the website. My goal was &#8230; more &#x2192;\n",
  "categories": [
    "general"
  ],
  "tags": [
    "Territorial Prison",
    "Wyoming"
  ],
  "publishedDate": "2009-04-28T20:05:12",
  "updatedAt": "2009-04-28T20:05:12",
  "wordpressId": 591
}